fairiskdata/__init__.py
fairiskdata/fairisk_dataset.py
fairiskdata/modelling/__init__.py
fairiskdata/modelling/excess_mortality.py
fairiskdata/preprocessing/__init__.py
fairiskdata/preprocessing/age_resampling.py
fairiskdata/preprocessing/normalizers.py
fairiskdata/preprocessing/resampling.py
fairiskdata/sources/__init__.py
fairiskdata/sources/covid_owid.py
fairiskdata/sources/dataset.py
fairiskdata/sources/eurostat.py
fairiskdata/sources/gho.py
fairiskdata/sources/inform.py
fairiskdata/sources/mobility_fb.py
fairiskdata/sources/mortality_hmd.py
fairiskdata/sources/single_dataset.py
fairiskdata/utils/__init__.py
fairiskdata/utils/age_parsers.py
fairiskdata/utils/fairisk_dataset_json_schema_creator.py
fairiskdata/utils/parsers.py
fairiskdata/utils/time_parsers.py
tests/__init__.py
tests/fairisk_dataset_test.py
fairiskdata-1.0.dist-info/LICENSE.txt
fairiskdata-1.0.dist-info/METADATA
fairiskdata-1.0.dist-info/WHEEL
fairiskdata-1.0.dist-info/top_level.txt
fairiskdata-1.0.dist-info/RECORD
