Metadata-Version: 2.1
Name: fairiskdata
Version: 1.0
Summary: This package facilitates fetching and handling data related to COVID and estimation of related excess mortality
Home-page: https://github.com/fraunhoferportugal/fairisk
Author: Catarina Pires, Diana Gomes, David Ribeiro, Duarte Folgado, Ricardo Santos, Telmo Barbosa
Author-email: catarina.pires@fraunhofer.pt, diana.gomes@fraunhofer.pt, david.ribeiro@fraunhofer.pt, duarte.folgado@fraunhofer.pt, ricardo.santos@fraunhofer.pt, telmo.barbosa@fraunhofer.pt
License: Creative Commons BY-NC-SA 4.0
Platform: UNKNOWN
Classifier: Programming Language :: Python :: 3
Classifier: Operating System :: OS Independent
Requires-Python: >=3.7
Requires-Dist: country-converter (==0.7.2)
Requires-Dist: mergedeep (==1.3.4)
Requires-Dist: simplejson (==3.17.2)
Requires-Dist: pyjstat (==2.2.0)
Requires-Dist: requests-futures (==1.0.0)
Requires-Dist: hdx-python-api (==4.9.5)
